backoff/__init__.py
backoff/_async.py
backoff/_common.py
backoff/_decorator.py
backoff/_jitter.py
backoff/_sync.py
backoff/_typing.py
backoff/_wait_gen.py
backoff/py.typed
backoff/types.py
backoff-2.2.0.dist-info/LICENSE
backoff-2.2.0.dist-info/WHEEL
backoff-2.2.0.dist-info/METADATA
backoff-2.2.0.dist-info/RECORD
